{
  "forceBlank": false,
  "uuid": "sweat & glitter night",
  "title": "Sweat & Glitter Night",
  "entryType": "Musik",
  "typeComplement": "Party",
  "desc": "Nachdem wir unsere Helferli von den Porny Days 2019 im privaten Rahmen orgasmisch beglückt haben, heizen wir dem Sender ab 22h00 mit viel Pornyness ein.\n\nab 18h30 Porny-Helferessen (privater Anlass)\\\nab 22h00 Sweat & Glitter Night (offen für alle)\\\n\\\n\\*\\**\\\n\\\nZur aktuellen Situation:\n\nACHTUNG! Aufgrund der Bestimmungen des Kanton Zürichs dürfen max. 100 Personen gleichzeitig im Club sein. Deshalb kann es zu längeren Wartezeiten kommen.\\\n\\\nAlle Gäste sind bei jedem Besuch verpflichtet, Vorname, Name und Telefonnummer anzugeben. Die gesammelten Daten werden vom Sender auf Aufforderung der kantonalen Gesundheitsbehörde während 14 Tagen nach der Veranstaltung ausgewiesen. Danach werden diese vernichtet und nicht anders verwendet.\n\nDas Risiko besteht, dass bei einem potenziellen Ansteckungsfall mit SARS-CoV-2 sämtliche an dem Anlass anwesenden Gäste in Quarantäne geschickt werden. Personen die der Risikogruppe (gemäss Definition des BAG) angehören raten wir von einem Besuch ab.",
  "additionalImages": [
    {
      "image": "/images/uploads/playlove.jpg"
    },
    {
      "image": "/images/uploads/miakaltes.jpg"
    }
  ],
  "image": "/images/uploads/porny-glitter.jpg"
}
