{
  "forceBlank": true,
  "authorCountry": "Australien",
  "entryType": "Film",
  "yearOfProduction": 2025,
  "deactivated": false,
  "desc": "Die introvertierte Prinzessin Saira, Tochter der lesbischen Königinnen des Planeten Clitopolis, ist am Boden zerstört: Ihre Freundin, die Kopfgeldjägerin Kiki, hat mit ihr Schluss gemacht! Saira sei einfach zu langweilig, sagt sie. Dabei hat sie ihr ein so schönes Beziehungsalbum gebastelt! Doch als Kiki von den Straight White Maliens, den Incels der Zukunft, entführt wird, muss Saira den Safe Space des queeren Weltraums verlassen und binnen 24 Stunden das Lösegeld überbringen: die königliche Labrys – eine goldene Doppelaxt von schier unglaublicher lesbischer Macht. Das einzige Problem… Saira hat sie nicht!",
  "duration": "87 Minutes",
  "videourl": "https://vimeo.com/1108068215",
  "authorName": "Emma HOUGH HOBBS & Leela VARGHESE",
  "title": "Lesbian Space Princess",
  "image": "/images/uploads/01_lesbian_space.jpg",
  "uuid": "lesbian-space-princess",
  "warning": "",
  "additionalImages": [
    {
      "image": "/images/uploads/03_lesbian_space.jpg"
    },
    {
      "image": "/images/uploads/05_lesbian_space.jpg"
    }
  ]
}