{
  "forceBlank": false,
  "authorCountry": "Chile",
  "entryType": "Film",
  "yearOfProduction": 2020,
  "deactivated": false,
  "desc": "Jedes Insekt in seinem Abteil. Die Körper beginnen sich langsam zu verweben, entdecken Kollektivität. Natürlich und spontan begeben sie sich durch Bewegung auf eine Reise, in der Sehnsucht nach Freiheit.",
  "duration": "10 Minutes",
  "videourl": "",
  "authorName": "Fernanda GALLARDO & María CATALINA",
  "title": "Mosquerío",
  "image": "/images/uploads/01_mosquerío.jpeg",
  "uuid": "mosquero",
  "warning": "",
  "additionalImages": [
    {
      "image": "/images/uploads/02_mosquerío.jpeg"
    }
  ]
}