{
  "forceBlank": false,
  "authorCountry": "Deutschland",
  "entryType": "Film",
  "yearOfProduction": 2025,
  "deactivated": false,
  "desc": "Ein berüchtigter Ausflug in den Lebensmittelladen, in einer einzigen Einstellung gedreht, mit Kommentar der Regie.",
  "duration": "20 Min, Englisch",
  "videourl": "",
  "authorName": "Ty Wardwell & Ethan Folk",
  "title": " Breakfast in Bed: Uncut Director’s Cut: A Walk to Remember ",
  "image": "/images/uploads/02_breakfast_in_bed.jpg",
  "uuid": "breakfast-in-bed-un cut",
  "warning": "",
  "additionalImages": []
}