{
  "typeComplement": "Dokuporn",
  "forceBlank": false,
  "entryType": "Film",
  "deactivated": false,
  "desc": "Ethan Folk/Ty Wardwell\\\nDeutschland, 2020, 13 Min, Englisch\n\nMes Chéris ist der Abschied eines Transbois von seinen Brüsten. Einen Monat vor seiner Mastektomie schlüpft Bat Boi in die Rolle von Chéri, einer Figur, die seinen Erfahrungen als wilde Fem Sexarbeiterin nachempfunden ist. Diese schlüpfrige Hommage untergräbt die Tropen des Heteropornos und der Mainstream-Trans*-Darstellung in einem radikalen Akt der Selbstliebe.",
  "videourl": "",
  "title": "Mes Chéris",
  "image": "/images/uploads/mes_cheris_02.jpg.jpg",
  "uuid": "mes-cheris",
  "warning": "",
  "additionalImages": [
    {
      "image": "/images/uploads/mes_cheris_03.jpg.jpg"
    },
    {
      "image": "/images/uploads/mes_cheris_04.jpg.jpg"
    }
  ]
}