{
  "forceBlank": false,
  "deactivated": false,
  "uuid": "nexus",
  "title": "NEXUS ",
  "entryType": "Performance",
  "typeComplement": "",
  "desc": "[](https://nexuscollective.ch)Wie verändert sich meine Wahrnehmung, wenn ich mit verbundenen Augen esse? Kann ein Geruch Lust entfachen? Wie verändert sich mein Körpergefühl, wenn Texturen sich unerwartet anfühlen? Kann beim gegenseitigen füttern Intimität und Vertrauen aufgebaut werden? \n\nDas [NEXUS](https://nexuscollective.ch) Collective entspringt einer geteilten Lust am Gestalten und dem Drang, verschiedene Perspektiven auf die Welt zu eröffnen, jenseits dominanter Erzählungen. Wir begreifen Nahrung als künstlerisches Medium und zentrales Element kultureller Identitätsbildung. Darin spiegeln sich die Strukturen, anhand derer wir unsere Umwelt formen, prägen und miteinander in Beziehung treten.\n\n**Kommt allein oder mit euren Liebsten und erkundet, wie Essen und Begehren sich verweben.**",
  "image": "/images/uploads/satisfy_my_hunger_1.jpg"
}