{
  "uuid": "nacer-ceniza-morir-maleza--film-291",
  "title": "Nacer ceniza, morir maleza",
  "entryType": "Film",
  "authorName": "Diego ARGOTE",
  "authorCountry": "Chile",
  "yearOfProduction": 2020,
  "duration": "3 Minutes",
  "desc": "<p>\"Nacer ceniza, morir maleza\" (\"Born Ashes, Die Weeds\") is a video-performance where an anonymous, masked body takes presence in a specific area of Santiago, Chile. This body, born of rage and ashes, rejects its own masculine traits—those that biologically govern it.</p>",
  "warning": "",
  "image": "",
  "additionalImages": [],
  "videourl": "",
  "forceBlank": false,
  "deactivated": false
}