{
  "typeComplement": "Doku",
  "forceBlank": false,
  "entryType": "Film",
  "deactivated": false,
  "desc": "Michelle Handelman\\\nUSA 1995; 70 Min., Englisch\n\n«Ein Blick in die lesbische S/M-Szene von San Francisco. Anhand von Collagen und Interviews hat Michelle Handelman ein buntes Insiderinnen-Mosaik zusammengestellt. Von der internationalen Ms Leather über die ‹Dyke Daddy› bis zur Frau von nebenan sammelte Handelman Stimmen und Statements nicht nur zu den individuellen Sexpraktiken, sondern auch mit Blickwinkel auf Politik und Gemeinschaft innerhalb der Szene. Speziell fokussiert werden acht Frauen, die im S/M sehr unterschiedliche Standpunkte einnehmen. Sie erzählen, wie sie ihren Weg zur ‹Francisco leather dyke community›gefunden haben, und nehmen die Zuschauerinnen mit in ihre Welt» \n\n• Xenia-Programm «Stonewall» – Juni/Juli 1996",
  "title": "Bloodsisters",
  "image": "/images/uploads/bloodsisters_02.jpeg",
  "uuid": "bloodsisters",
  "warning": ""
}